langgraph_unity_catalog_checkpoint/__init__.py
langgraph_unity_catalog_checkpoint/logging_config.py
langgraph_unity_catalog_checkpoint/checkpoint/__init__.py
langgraph_unity_catalog_checkpoint/checkpoint/aio.py
langgraph_unity_catalog_checkpoint/checkpoint/base.py
langgraph_unity_catalog_checkpoint/checkpoint/shallow.py
langgraph_unity_catalog_checkpoint/checkpoint/unity_catalog.py
langgraph_unity_catalog_checkpoint/store/__init__.py
langgraph_unity_catalog_checkpoint/store/aio.py
langgraph_unity_catalog_checkpoint/store/base.py
langgraph_unity_catalog_checkpoint/store/unity_catalog.py
langgraph_unity_catalog_checkpoint-0.0.2.dist-info/licenses/LICENSE
langgraph_unity_catalog_checkpoint-0.0.2.dist-info/METADATA
langgraph_unity_catalog_checkpoint-0.0.2.dist-info/WHEEL
langgraph_unity_catalog_checkpoint-0.0.2.dist-info/top_level.txt
langgraph_unity_catalog_checkpoint-0.0.2.dist-info/RECORD
