Metadata-Version: 2.4
Name: langgraph-unity-catalog-checkpoint
Version: 0.0.2
Summary: Unity Catalog-backed persistence for LangChain and LangGraph
Author-email: Nate Fleming <nate.fleming@databricks.com>
Maintainer-email: Nate Fleming <nate.fleming@databricks.com>
License-Expression: MIT
Project-URL: Homepage, https://github.com/natefleming/langgraph_unity_catalog_checkpoint
Project-URL: Repository, https://github.com/natefleming/langgraph_unity_catalog_checkpoint
Project-URL: Issues, https://github.com/natefleming/langgraph_unity_catalog_checkpoint/issues
Project-URL: Documentation, https://github.com/natefleming/langgraph_unity_catalog_checkpoint#readme
Keywords: langchain,langgraph,databricks,unity-catalog,checkpoint,persistence,store,memory,agents,llm,ai
Classifier: Development Status :: 3 - Alpha
Classifier: Intended Audience :: Developers
Classifier: Intended Audience :: Science/Research
Classifier: Operating System :: OS Independent
Classifier: Programming Language :: Python :: 3
Classifier: Programming Language :: Python :: 3.12
Classifier: Programming Language :: Python :: 3.13
Classifier: Topic :: Scientific/Engineering :: Artificial Intelligence
Classifier: Topic :: Software Development :: Libraries :: Python Modules
Classifier: Topic :: Database
Classifier: Typing :: Typed
Requires-Python: >=3.12
License-File: LICENSE
Requires-Dist: databricks-connect>=17.0.10
Requires-Dist: databricks-langchain>=0.9.0
Requires-Dist: databricks-sdk>=0.73.0
Requires-Dist: langchain>=1.0.3
Requires-Dist: langgraph>=1.0.2
Requires-Dist: langmem>=0.0.30
Requires-Dist: loguru>=0.7.3
Requires-Dist: mlflow==3.5.1
Requires-Dist: nest-asyncio>=1.6.0
Requires-Dist: python-dotenv>=1.2.1
Provides-Extra: dev
Requires-Dist: pytest>=8.4.2; extra == "dev"
Requires-Dist: pytest-asyncio>=0.23.0; extra == "dev"
Requires-Dist: pytest-cov>=4.1.0; extra == "dev"
Requires-Dist: ruff>=0.6.0; extra == "dev"
Requires-Dist: twine>=5.0.0; extra == "dev"
Requires-Dist: python-dotenv>=1.0.0; extra == "dev"
Dynamic: license-file
